README.md
pyproject.toml
setup.cfg
setup.py
vellum/__init__.py
vellum/py.typed
vellum/api_resources/__init__.py
vellum/api_resources/completion_actuals.py
vellum/api_resources/generate.py
vellum/api_resources/search.py
vellum/api_resources/types.py
vellum/api_resources/upload_document.py
vellum/api_resources/abstract/__init__.py
vellum/api_resources/abstract/api_resource.py
vellum/api_resources/abstract/documents_api_resource.py
vellum/api_resources/abstract/exceptions.py
vellum/api_resources/abstract/predict_api_resource.py
vellum_client.egg-info/PKG-INFO
vellum_client.egg-info/SOURCES.txt
vellum_client.egg-info/dependency_links.txt
vellum_client.egg-info/requires.txt
vellum_client.egg-info/top_level.txt