Metadata-Version: 1.0
Name: vellum-client
Version: 0.0.12
Summary: Vellum Python client
Home-page: http://github.com/vocify/vellum-client-python
Author: vellum.ai
Author-email: devops@vellum.ai
License: UNKNOWN
Platform: UNKNOWN
